libpsf.cpython-311-x86_64-linux-gnu.so
libpsf.libs/libpsf-747b0b47.so.0
libpsf.libs/libboost_python311-01a00564.so.1.80.0
libpsf-0.1.4.dist-info/RECORD
libpsf-0.1.4.dist-info/METADATA
libpsf-0.1.4.dist-info/WHEEL
libpsf-0.1.4.dist-info/top_level.txt
tests/__init__.py
tests/test_psfdataset.py
