Metadata-Version: 2.1
Name: libpsf
Version: 0.1.4
Summary: library to read Cadence PSF output
Home-page: https://gitlab.com/bjmuld/libpsf-python/wikis/home
Author: Barry Muldrey, originally Henrik Johansen
Author-email: barry@muldrey.net
License: GNU Lesser General Public License v3.0
Project-URL: Bug Tracker, https://gitlab.com/bjmuld/libpsf-python/issues
Project-URL: Documentation, https://gitlab.com/bjmuld/libpsf-python/wikis/home
Project-URL: Source Code, https://gitlab.com/bjmuld/libpsf-python
Keywords: cadence,spectre,virtuoso,circtuit,simulation,waveform,circuit simulation
Platform: UNKNOWN
Requires-Dist: numpy (>=1.10.0)
